ciutils.py
setup.py
ciutils.egg-info/PKG-INFO
ciutils.egg-info/SOURCES.txt
ciutils.egg-info/dependency_links.txt
ciutils.egg-info/requires.txt
ciutils.egg-info/top_level.txt