Metadata-Version: 1.0
Name: ciutils
Version: 0.0.6
Summary: Helpers to use in CI environments (e.g. use xmlrunner with `test` command)
Home-page: UNKNOWN
Author: Olemis Lang
Author-email: olemis+py@gmail.com
License: UNKNOWN
Platform: UNKNOWN
